locust_nest/__init__.py
locust_nest/configure.py
locust_nest/helpers.py
locust_nest/install.py
locust_nest/main.py
locust_nest/nest.py
locust_nest/version.py
locust_nest/example/README.md
locust_nest/example/example.py
locust_nest/example/example.pyc
locust_nest/example/run_load_tests.sh
locust_nest-0.39.dist-info/METADATA
locust_nest-0.39.dist-info/RECORD
locust_nest-0.39.dist-info/WHEEL
locust_nest-0.39.dist-info/entry_points.txt
locust_nest-0.39.dist-info/top_level.txt
