Metadata-Version: 1.2
Name: locust-nest
Version: 0.39
Summary: Auto-import and compilation of locust TaskSets.
Home-page: https://github.com/ps-george/locust-nest
Author: George Punter
Author-email: puntersg@gmail.com
License: MIT
Platform: UNKNOWN
Classifier: License :: OSI Approved :: MIT License
Classifier: Programming Language :: Python
Classifier: Programming Language :: Python :: 2
Classifier: Programming Language :: Python :: 2.7
Classifier: Programming Language :: Python :: 3
Classifier: Programming Language :: Python :: 3.6
Classifier: Programming Language :: Python :: Implementation :: CPython
Classifier: Programming Language :: Python :: Implementation :: PyPy
Requires-Python: >=2.7.0
